pypkgs_mk/__init__.py
pypkgs_mk/pypkgs_mk.py
pypkgs_mk-0.1.0.dist-info/LICENSE
pypkgs_mk-0.1.0.dist-info/WHEEL
pypkgs_mk-0.1.0.dist-info/METADATA
pypkgs_mk-0.1.0.dist-info/RECORD
