Metadata-Version: 2.1
Name: pypkgs-mk
Version: 0.1.0
Summary: A sample python package for week 1
License: MIT
Author: Micah Kwok
Author-email: micahkwok@gmail.com
Requires-Python: >=3.8,<4.0
Classifier: License :: OSI Approved :: MIT License
Classifier: Programming Language :: Python :: 3
Classifier: Programming Language :: Python :: 3.8
Classifier: Programming Language :: Python :: 3.9
Requires-Dist: pandas (>=1.2.2,<2.0.0)
